[
  {
    "ID": 1,
    "MachineMode": 0,
    "GoalType": 0,
    "ShowType": 0,
    "UIDistance": [
      10
    ],
    "WallDistance": [
      400
    ],
    "Tip": 30279
  },
  {
    "ID": 2,
    "MachineMode": 0,
    "GoalType": 1,
    "ShowType": 0,
    "UIDistance": [
      20,
      20,
      20
    ],
    "WallDistance": [
      400,
      800,
      800
    ],
    "Tip": 30279
  },
  {
    "ID": 3,
    "MachineMode": 0,
    "GoalType": 0,
    "ShowType": 1,
    "UIDistance": [
      1
    ],
    "WallDistance": [
      50
    ],
    "Tip": 30279
  },
  {
    "ID": 4,
    "MachineMode": 0,
    "GoalType": 1,
    "ShowType": 1,
    "UIDistance": [
      1,
      1,
      1
    ],
    "WallDistance": [
      20,
      50,
      80
    ],
    "Tip": 30279
  },
  {
    "ID": 5,
    "MachineMode": 0,
    "GoalType": 0,
    "ShowType": 2,
    "UIDistance": [
      3
    ],
    "WallDistance": [
      300
    ],
    "Tip": 30279
  },
  {
    "ID": 6,
    "MachineMode": 0,
    "GoalType": 1,
    "ShowType": 2,
    "UIDistance": [
      3,
      3,
      3
    ],
    "WallDistance": [
      300,
      600,
      600
    ],
    "Tip": 30279
  },
  {
    "ID": 7,
    "MachineMode": 2,
    "GoalType": 0,
    "ShowType": 0,
    "UIDistance": [
      50
    ],
    "WallDistance": [
      800
    ],
    "Tip": 30279
  },
  {
    "ID": 8,
    "MachineMode": 2,
    "GoalType": 1,
    "ShowType": 0,
    "UIDistance": [
      50,
      50,
      50
    ],
    "WallDistance": [
      800,
      1600,
      1600
    ],
    "Tip": 30279
  },
  {
    "ID": 9,
    "MachineMode": 2,
    "GoalType": 0,
    "ShowType": 1,
    "UIDistance": [
      1
    ],
    "WallDistance": [
      50
    ],
    "Tip": 30279
  },
  {
    "ID": 10,
    "MachineMode": 2,
    "GoalType": 1,
    "ShowType": 1,
    "UIDistance": [
      1,
      1,
      1
    ],
    "WallDistance": [
      20,
      50,
      80
    ],
    "Tip": 30279
  },
  {
    "ID": 11,
    "MachineMode": 2,
    "GoalType": 0,
    "ShowType": 2,
    "UIDistance": [
      3
    ],
    "WallDistance": [
      300
    ],
    "Tip": 30279
  },
  {
    "ID": 12,
    "MachineMode": 2,
    "GoalType": 1,
    "ShowType": 2,
    "UIDistance": [
      3,
      3,
      3
    ],
    "WallDistance": [
      300,
      600,
      600
    ],
    "Tip": 30279
  },
  {
    "ID": 13,
    "MachineMode": -1,
    "GoalType": 1,
    "ShowType": 0,
    "UIDistance": [
      20,
      20,
      20,
      20,
      20
    ],
    "WallDistance": [
      50,
      150,
      250,
      350,
      400
    ],
    "Tip": 30287
  }
]